AUTHORS
LICENSE.txt
MANIFEST.in
README.rst
pyproject.toml
setup.cfg
setup.py
setup_util.py
versioneer.py
pyEMMA.egg-info/PKG-INFO
pyEMMA.egg-info/SOURCES.txt
pyEMMA.egg-info/dependency_links.txt
pyEMMA.egg-info/entry_points.txt
pyEMMA.egg-info/not-zip-safe
pyEMMA.egg-info/requires.txt
pyEMMA.egg-info/top_level.txt
pyemma/__init__.py
pyemma/_version.py
pyemma/logging.yml
pyemma/pyemma.cfg
pyemma/_base/__init__.py
pyemma/_base/estimator.py
pyemma/_base/loggable.py
pyemma/_base/model.py
pyemma/_base/parallel.py
pyemma/_base/progress/__init__.py
pyemma/_base/progress/test_progress.py
pyemma/_base/progress/reporter/__init__.py
pyemma/_base/serialization/__init__.py
pyemma/_base/serialization/cli.py
pyemma/_base/serialization/h5file.py
pyemma/_base/serialization/mdtraj_helpers.py
pyemma/_base/serialization/pickle_extensions.py
pyemma/_base/serialization/serialization.py
pyemma/_base/serialization/util.py
pyemma/_base/serialization/tests/__init__.py
pyemma/_base/serialization/tests/_test_classes.py
pyemma/_base/serialization/tests/test_cli.py
pyemma/_base/serialization/tests/test_serialization.py
pyemma/_base/serialization/tests/test_topology.py
pyemma/_base/tests/__init__.py
pyemma/_base/tests/test_estimator.py
pyemma/_ext/__init__.py
pyemma/_ext/orderedset/__init__.py
pyemma/_ext/orderedset/_orderedset.pyx
pyemma/_ext/sklearn/__init__.py
pyemma/_ext/sklearn/base.py
pyemma/_ext/sklearn/parameter_search.py
pyemma/_ext/variational/__init__.py
pyemma/_ext/variational/util.py
pyemma/_ext/variational/estimators/__init__.py
pyemma/_ext/variational/estimators/moments.py
pyemma/_ext/variational/estimators/running_moments.py
pyemma/_ext/variational/estimators/covar_c/__init__.py
pyemma/_ext/variational/estimators/covar_c/covartools.cpp
pyemma/_ext/variational/estimators/covar_c/covartools.py
pyemma/_ext/variational/estimators/covar_c/covartools_cpp.h
pyemma/_ext/variational/estimators/tests/__init__.py
pyemma/_ext/variational/estimators/tests/benchmark_moments.py
pyemma/_ext/variational/estimators/tests/test_moments.py
pyemma/_ext/variational/estimators/tests/test_running_moments.py
pyemma/_ext/variational/solvers/__init__.py
pyemma/_ext/variational/solvers/direct.py
