Metadata-Version: 2.1
Name: pyEMMA
Version: 2.5.12
Summary: PyEMMA: Emma's Markov Model Algorithms
Home-page: http://github.com/markovmodel/PyEMMA
Author: The Emma team
Author-email: info@emma-project.org
Maintainer: Martin K. Scherer
Maintainer-email: m.scherer@fu-berlin.de
License: LGPLv3+
Keywords: Markov State Model Algorithms
Platform: Windows
Platform: Linux
Platform: Solaris
Platform: Mac OS-X
Platform: Unix
Classifier: Development Status :: 5 - Production/Stable
Classifier: Environment :: Console
Classifier: Environment :: MacOS X
Classifier: Intended Audience :: Science/Research
Classifier: License :: OSI Approved :: GNU Lesser General Public License v3 or later (LGPLv3+)
Classifier: Natural Language :: English
Classifier: Operating System :: MacOS :: MacOS X
Classifier: Operating System :: POSIX
Classifier: Operating System :: Microsoft :: Windows
Classifier: Programming Language :: Python :: 2.7
Classifier: Programming Language :: Python :: 3
Classifier: Topic :: Scientific/Engineering :: Bio-Informatics
Classifier: Topic :: Scientific/Engineering :: Chemistry
Classifier: Topic :: Scientific/Engineering :: Mathematics
Classifier: Topic :: Scientific/Engineering :: Physics
License-File: LICENSE.txt
License-File: AUTHORS
